{
  "users": [
    {
      "userId": "user1",
      "password": "user1",
      "plants": [
        {
          "plantId": "plant1",
          "code": "ABCDEF",
          "ownerId": "user1",
          "plantType": "Evergreen"
        }
      ]
    },
    {
      "userId": "user2",
      "password": "user2",
      "plants": [
        {
          "plantId": "plant2",
          "code": "",
          "ownerId": "user2",
          "plantType": "Evergreen"
        }
      ]
    },
    {
      "userId": "user3",
      "password": "user3",
      "plants": []
    },
    {
      "userId": "user4",
      "password": "user4",
      "plants": [
        {
          "plantId": "plant4",
          "code": "",
          "ownerId": "user4",
          "plantType": "Evergreen"
        }
      ]
    },
    {
      "userId": "user5",
      "password": "user5",
      "plants": []
    }
  ]
}
